crec_annotator/__init__.py
crec_annotator/main.py
crec_annotator-24.11.6.0.dist-info/LICENSE
crec_annotator-24.11.6.0.dist-info/METADATA
crec_annotator-24.11.6.0.dist-info/WHEEL
crec_annotator-24.11.6.0.dist-info/entry_points.txt
crec_annotator-24.11.6.0.dist-info/top_level.txt
crec_annotator-24.11.6.0.dist-info/RECORD
