Metadata-Version: 2.1
Name: crec_annotator
Version: 24.11.6.0
Summary: A tool to annotate and view congressional record text files.
Home-page: https://github.com/YZhang-Jeremy/crec_annotator/
Author: Yichi Zhang
Author-email: yichizhang2002@gmail.com
Classifier: License :: OSI Approved :: GNU General Public License v3 (GPLv3)
Classifier: Programming Language :: Python :: 3
Classifier: Operating System :: OS Independent
Requires-Python: >=3.10
License-File: LICENSE
